LICENSE
MANIFEST.in
README.md
pyproject.toml
pykwalify_webform/__init__.py
pykwalify_webform/__main__.py
pykwalify_webform/renderer.py
pykwalify_webform.egg-info/PKG-INFO
pykwalify_webform.egg-info/SOURCES.txt
pykwalify_webform.egg-info/dependency_links.txt
pykwalify_webform.egg-info/entry_points.txt
pykwalify_webform.egg-info/requires.txt
pykwalify_webform.egg-info/top_level.txt
pykwalify_webform/static/main.js
pykwalify_webform/static/tagsinput/LICENSE
pykwalify_webform/static/tagsinput/README.md
pykwalify_webform/static/tagsinput/package.json
pykwalify_webform/static/tagsinput/tagsinput.css
pykwalify_webform/static/tagsinput/tagsinput.js
pykwalify_webform/templates/form_group.jinja2
pykwalify_webform/templates/page.jinja2
pykwalify_webform/templates/types/any.jinja2
pykwalify_webform/templates/types/date.jinja2
pykwalify_webform/templates/types/int.jinja2
pykwalify_webform/templates/types/map.jinja2
pykwalify_webform/templates/types/seq.jinja2
pykwalify_webform/templates/types/str.jinja2
pykwalify_webform/templates/types/text.jinja2