Metadata-Version: 2.1
Name: pykwalify-webform
Version: 0.2.2
Summary: Generate webforms based on YAML schema with pykwalify
Author-email: congusbongus <congusbongus@gmail.com>
License: MIT License
Project-URL: Repository, https://github.com/cxong/pykwalify-webform
Classifier: Development Status :: 3 - Alpha
Classifier: Intended Audience :: Developers
Classifier: Topic :: Internet :: WWW/HTTP :: Dynamic Content
Classifier: License :: OSI Approved :: MIT License
Classifier: Programming Language :: Python :: 3
Classifier: Programming Language :: Python :: 3.7
Classifier: Programming Language :: Python :: 3.8
Classifier: Programming Language :: Python :: 3.9
Classifier: Programming Language :: Python :: 3.10
Classifier: Programming Language :: Python :: 3.11
Classifier: Programming Language :: Python :: 3.12
Requires-Python: >=3.7
License-File: LICENSE
Requires-Dist: click>=8.1.8
Requires-Dist: jinja2>=3.1.5
Requires-Dist: pykwalify>=1.8.0
